LICENSE
MANIFEST.in
README.md
requirements.txt
setup.cfg
setup.py
medikalnet/__init__.py
medikalnet/__version__.py
medikalnet/segmentation.py
medikalnet.egg-info/PKG-INFO
medikalnet.egg-info/SOURCES.txt
medikalnet.egg-info/dependency_links.txt
medikalnet.egg-info/requires.txt
medikalnet.egg-info/top_level.txt