Metadata-Version: 2.1
Name: medikalnet
Version: 0.0.1a14
Summary: Deep Medical Imaging. Keras.
Home-page: https://github.com/SamSepi0l59/medikalnet
Author: Vignesh Kotteeswaran
Author-email: iamvk888@gmail.com
License: MIT
Platform: UNKNOWN
Classifier: License :: OSI Approved :: MIT License
Classifier: Programming Language :: Python
Classifier: Programming Language :: Python :: 3
Classifier: Programming Language :: Python :: Implementation :: CPython
Classifier: Programming Language :: Python :: Implementation :: PyPy
Requires-Python: >=3.0.0
Provides-Extra: tests
